<?xml version="1.0" ?><!DOCTYPE TEI.2  PUBLIC '-//TEI//DTD TEI Lite XML ver. 1//EN'  'file:/c:/app/usr/dtds/teixlite.dtd'><tei.2>
  <teiheader>
    <filedesc>
      <titlestmt>
	<title>SSSC 05: Wisahketchahk Stabs a Buffalo and Both His Arms</title>
	<author>Coming-Day</author>
	<respstmt>
	  <name>Kevin Russell</name>
	  <resp>TEI markup and word-tagging</resp>
	</respstmt>
      </titlestmt>
      <publicationstmt>
	<authority>Cree Text Project</authority>
	<address>
	  <addrline>Linguistics Department</addrline>
	  <addrline>University of Manitoba</addrline>
	  <addrline>Winnipeg, MB  R3T 2N2  Canada</addrline>
	</address>
	<availability>
	  <p>for internal use only</p>
	</availability>
      </publicationstmt>
      <sourcedesc>
	<bibl>
          <title>Sacred Stories of the Sweet Grass Cree</title>
          <editor>Leonard Bloomfield</editor>
          <date>1930</date>
          <publisher>F.A. Acland, King's Printer</publisher>
          <pubplace>Ottawa</pubplace>
          <series>National Museum of Canada, Bulletin no. 60, Anthropological Series, no. 11</series>
          <biblscope>pages 32-34</biblscope>
        </bibl>
      </sourcedesc>
    </filedesc>
    <encodingdesc>
      <p/>
      <p>This electronic document is oriented more toward representing those
      features that seem most likely to be relevant for grammatical analyses,
      rather than toward faithfully representing all the information available in
      the book.</p>
    </encodingdesc>
    <profiledesc>
      <langusage>
	<language id="x-neh">Plains Cree</language>
	<language id="eng">English</language>
      </langusage>
    </profiledesc>
    <revisiondesc>
      <list>
        <item>2004 04 01; KR; inauguration</item>
        <item>2014 06 10; KR; UTF-8, paragraph and sentence numbering, smart-quotes in English translations</item>
      </list>
    </revisiondesc>
  </teiheader>
  <text>
    <body>

<head>Sacred Stories 05:  Wisahketchahk Stabs a Buffalo and Both His Arms</head>
<docauthor>Coming-Day</docauthor>

<p n="1">

<seg n="1.1">
<w canon="kêtahtawê" class="ipc" gcat="IPC" sgloss="at_times" stem="kêtahtawê">kêtahtawê</w>
<w canon="pimohtêw" class="vai" gcat="3sAI" sgloss="go_along" stem="pimohtê" suffix="-w">pimohtêw</w>
<w canon="wîsahkêcâhk" class="na" gcat="3sNA" sgloss="Wisahketchahk" stem="wîsahkêcâhkw" suffix="0">wîsahkêcâhk</w>
;
<w canon="mâka" class="ipc" gcat="IPC" sgloss="but" stem="mâka">mâka</w>
<w canon="mîna" class="ipc" gcat="IPC" sgloss="also" stem="mîna">mînah</w>
<w canon="nôhtêhkatêw" class="vai" gcat="3sAI" sgloss="be_hungry" stem="nôhtêhkatê" suffix="-w">nôhtêhkatêw</w>
.
<gloss>Once upon a time Wisahketchahk was walking along; as usual, he was hungry.</gloss>
</seg>

<seg n="1.2">
<w canon="kîtahtawê" class="ipc" gcat="IPC" sgloss="at_times" stem="kêtahtawê">kîtahtawê</w>
<w canon="wâpamêw" class="vta" gcat="3s3oTA" sgloss="see" stem="wâpam" suffix="-êw">wâpamêw</w>
<w canon="mostoswa" class="na" gcat="3oNA" sgloss="cattle" stem="mostosw" suffix="-a">mostoswah</w>
<w canon="nîso" class="ipc" gcat="IPC" sgloss="two" stem="nîso">nîso</w>
,
<w canon="takwahinâwa" class="na" gcat="3oNA" sgloss="bull" stem="takwahinâw" suffix="-a">takwahnawah</w>
<w canon="pêyak" class="ipc" gcat="IPC" sgloss="one" stem="pêyak">pêyak</w>
,
<w canon="pêyak" class="ipc" gcat="IPC" sgloss="one" stem="pêyak">pêyak</w>
<w canon="iyâpêsisa" class="na" gcat="3oNA" sgloss="young_bull" stem="iyâpêsis" suffix="-a">iyâpêsisah</w>
.
<gloss>Presently he saw two buffalos, a bull and a young steer.</gloss>
</seg>
</p>

<p n="2">

<seg n="2.1">
<w canon="ômisi" class="ipc" gcat="IPC" sgloss="thus" stem="ômisi">ômisi</w>
<w canon="itêyihtam" class="vti" gcat="3sTI" sgloss="think_of" stem="itêyiht" suffix="-am">itêyihtam</w>
:
<q>
<w canon="tânisi" class="ipc" gcat="IPC" sgloss="how" stem="tânisi">tânisih</w>
<w canon="nika-nipahâwak" class="vta" gcat="1s3pTA" prefix="1" preverbs="ka|will" sgloss="kill" stem="nipah" suffix="-âwak">nika-nipahâwak</w>
?</q>
<w canon="itêyihtam" class="vti" gcat="3sTI" sgloss="think_of" stem="itêyiht" suffix="-am">itêyihtam</w>
.
<gloss>This is what he thought: “How shall I kill them?” he thought.</gloss>
</seg>
</p>

<p n="3">

<seg n="3.1">
<w canon="nama" class="ipc" gcat="IPC" sgloss="not" stem="nama">nama</w>
<w canon="kêkway" class="pr" gcat="0sPR" sgloss="something" stem="kîkway">kêkway</w>
<w canon="pâskisikan" class="ni" gcat="0sNI" sgloss="gun" stem="pâskisikan" suffix="0">pâskisikan</w>
<w canon="ayâw" class="vai" gcat="3sAI" sgloss="be" stem="ayâ" suffix="-w">ayâw</w>
.
<gloss>He had no gun.</gloss>
</seg>

<seg n="3.2">
<w canon="êkwa" class="ipc" gcat="IPC" sgloss="then" stem="êkwa">êkwah</w>
<w canon="sipwêhtêw" class="vai" gcat="3sAI" sgloss="leave" stem="sipwêhtê" suffix="-w">sipwêhtêw</w>
.
<gloss>Then he went from there.</gloss>
</seg>

<seg n="3.3">
<w canon="ê-wâpamikot" class="vta" gcat="3o3sTAcnj" preverbs="ê|cnj" sgloss="see" stem="wâpam" suffix="-ikot">êh-wâpamikot</w>
,
<w canon="wî-tapasîyiwa" class="vai" gcat="3oAI" preverbs="wî|will" sgloss="flee" stem="tapasî" suffix="-yiwa">wîh-tapasiyiwah</w>
.
<gloss>When they saw him, they wanted to run away.</gloss>
</seg>
</p>

<p n="4">

<seg n="4.1">
<q>
<w canon="cêskwa" class="ipc" gcat="IPC" sgloss="wait" stem="cêskwa">cêskwah</w>
,
<w canon="nisîmitik" class="nda" extra="vocp" gcat="3pNDAof1svoc" prefix="1" sgloss="younger_sib" stem="sîm" suffix="-VOCp">nisîmitik</w>
!
<w canon="miywâsin" class="vii" gcat="0sII" sgloss="be_good" stem="miywâsin" suffix="0">miywâsin</w>
<w canon="âcimowin" class="ni" gcat="0sNI" sgloss="story" stem="âcimowin" suffix="0">âcimowin</w>
<w canon="ka-âcimostâtinâwâw" class="vta" gcat="1s2pTA" preverbs="ka|will" sgloss="tell_about" stem="âcimostaw" suffix="-itinâwâw">k-âcimostâtinâwâw</w>
.</q>
<gloss>“Wait a bit, my little brothers. I shall tell you a good story!”</gloss>
</seg>
</p>

<p n="5">

<seg n="5.1">
<w canon="cêskwa" class="ipc" gcat="IPC" sgloss="wait" stem="cêskwa">cêskwah</w>
<w canon="nîpawiwak" class="vai" gcat="3pAI" sgloss="stand" stem="nîpawi" suffix="-wak">nîpawiwak</w>
<w canon="mostoswak" class="na" gcat="3pNA" sgloss="cattle" stem="mostosw" suffix="-ak">mostoswak</w>
;
<w canon="namôya" class="ipc" gcat="IPC" sgloss="not" stem="namôya">namowya</w>
<w canon="tapasîwak" class="vai" gcat="3pAI" sgloss="flee" stem="tapasî" suffix="-wak">tapasîwak</w>
.
<gloss>Soon the buffalos stood still; they did not run away.</gloss>
</seg>

<seg n="5.2">
<w canon="êkwa" class="ipc" gcat="IPC" sgloss="then" stem="êkwa">êkwah</w>
<w canon="takohtêw" class="vai" gcat="3sAI" sgloss="arrive" stem="takohtê" suffix="-w">takohtêw</w>
<w canon="wîsahkêcâhk" class="na" gcat="3sNA" sgloss="Wisahketchahk" stem="wîsahkêcâhkw" suffix="0">wîsahkêcâhk</w>
.
<gloss>Then Wisahketchahk walked up to them.</gloss>
</seg>
</p>

<p n="6">

<seg n="6.1">
<w canon="ômisi" class="ipc" gcat="IPC" sgloss="thus" stem="ômisi">ômisî</w>
<w canon="itêw" class="vta" gcat="3s3oTA" sgloss="say_to" stem="it" suffix="-êw">itêw</w>
:
<q rend="PRE 1 POST0">
<w canon="ayisiyiniwak" class="na" gcat="3pNA" sgloss="person" stem="ayisiyiniw" suffix="-ak">ayisiyiniwak</w>
<w canon="ê-itwêcik" class="vai" gcat="3pAIcnj" preverbs="ê|cnj" sgloss="say" stem="itwê" suffix="-cik">êh-itwêcik</w>
,
<q>
<w canon="takwahinâw" class="na" gcat="3sNA" sgloss="bull" stem="takwahinâw" suffix="0">takwahnaw</w>
<w canon="wîhkimâkosiw" class="vai" gcat="3sAI" sgloss="smell_good" stem="wîhkimâkosi" suffix="-w">wîhkimâkosiw</w>
;
<w canon="miyosiw" class="vai" gcat="3sAI" sgloss="be_good" stem="miyosi" suffix="-w">miyosiw</w>
,</q>
<w canon="ê-itwêcik" class="vai" gcat="3pAIcnj" preverbs="ê|cnj" sgloss="say" stem="itwê" suffix="-cik">êh-itwêcik</w>
,
<w canon="kotakak" class="pr" gcat="3pPR" sgloss="other" stem="kotak" suffix="-3p">kotakak</w>
<w canon="ayisiyiniwak" class="na" gcat="3pNA" sgloss="person" stem="ayisiyiniw" suffix="-ak">ayisiyiniwak</w>
<w canon="ômisi" class="ipc" gcat="IPC" sgloss="thus" stem="ômisi">ômisih</w>
<w canon="itwêwak" class="vai" gcat="3pAI" sgloss="say" stem="itwê" suffix="-wak">itwêwak</w>
:
<q>
<w canon="iyâpêsis" class="na" gcat="3sNA" sgloss="young_bull" stem="iyâpêsis" suffix="0">iyâpêsis</w>
<w canon="miyosiw" class="vai" gcat="3sAI" sgloss="be_good" stem="miyosi" suffix="-w">miyosiw</w>
;
<w canon="wîhkimâkosiw" class="vai" gcat="3sAI" sgloss="smell_good" stem="wîhkimâkosi" suffix="-w">wîhkimâkosiw</w>
,</q>
<w canon="ê-itwêcik" class="vai" gcat="3pAIcnj" preverbs="ê|cnj" sgloss="say" stem="itwê" suffix="-cik">êh-itwêcik</w>
,
<w canon="ê-kî-kîhkihtocik" class="vai" gcat="3pAIcnj" preverbs="ê|cnj kî|PAST" sgloss="resist_e.o." stem="kîhkihto" suffix="-cik">êh-kîh-kîhkihtocik</w>
.</q>
<gloss>This is what he said to them: “Some men said, ‘The bull smells good; he is beautiful,’ but then some others said, ‘The young steer is beautiful; he smells good,’ and so they quarrelled.</gloss>
</seg>

<seg n="6.2">
<q rend="PRE 0 POST0">
<w canon="êwako" class="pr" gcat="PR" sgloss="that_one" stem="êwako">êk</w>
<w canon="ohci" class="ipc" gcat="IPC" sgloss="thence" stem="ohci">ôhci</w>
<w canon="wî-kisiwâsiwak" class="vai" gcat="3pAI" preverbs="wî|will" sgloss="be_angry" stem="kisiwâsi" suffix="-wak">wîh-kisiwâsiwak</w>
.</q>
<gloss>On this account they were getting quite angry.</gloss>
</seg>

<seg n="6.3">
<q rend="PRE 0 POST1">
<q>
<w canon="mahti" class="ipc" gcat="IPC" sgloss="let's_see" stem="mahti">mahti</w>
<w canon="cêskwa" class="ipc" gcat="IPC" sgloss="wait" stem="cêskwa">cêskwah</w>
<w canon="niya" class="pr" gcat="1sPR" sgloss="I" stem="niya">niyah</w>
<w canon="nika-wâpamâwak" class="vta" gcat="1s3pTA" prefix="1" preverbs="ka|will" sgloss="see" stem="wâpam" suffix="-âwak">nika-wâpamâwak</w>
;
<w canon="awîna" class="pr" gcat="3sPRq" sgloss="who" stem="awîna">awînah</w>
<w canon="wîhkimâkosiw" class="vai" gcat="3sAI" sgloss="smell_good" stem="wîhkimâkosi" suffix="-w">wîhkimâkosiw</w>
,</q>
<w canon="nititwân" class="vai" gcat="1sAI" prefix="1" sgloss="say" stem="itwê" suffix="-n">nititwân</w>
,
<w canon="kâ-pê-nitawâpamitakok" class="vta" gcat="1s2pTAcnj" preverbs="kâ|cnj pê|thence" sgloss="go_to_see" stem="nitawâpam" suffix="-itakok">kâ-pê-nitawâpamitakok</w>
,</q>
<w canon="ê-wî-wayêsimât" class="vta" gcat="3s3oTAcnj" preverbs="ê|cnj wî|will" sgloss="trick_by_speech" stem="wayêsim" suffix="-ât">ê-wîh-wayêsimât</w>
<w canon="ôhi" class="dem" gcat="3oDEM" sgloss="this" stem="awa" suffix="-3o">ôhih</w>
<w canon="mostoswa" class="na" gcat="3oNA" sgloss="cattle" stem="mostosw" suffix="-a">mostoswah</w>
.
<gloss>‘Just wait a bit, while I go look at them to find out which smells better,’ said I, and so I have come to see you,” he spoke to deceive those buffalos.</gloss>
</seg>
</p>

<p n="7">

<seg n="7.1">
<w canon="tâpwê" class="ipc" gcat="IPC" sgloss="truly" stem="tâpwê">tâpwêh</w>
<w canon="tâpwêhtam" class="vti" gcat="3sTI" sgloss="agree_with" stem="tâpwêht" suffix="-am">tâpwêhtam</w>
<w canon="awa" class="dem" gcat="3sDEM" sgloss="this" stem="awa">awa</w>
<w canon="mostos" class="na" gcat="3sNA" sgloss="cattle" stem="mostosw" suffix="0">mostos</w>
.
<gloss>The buffalos really believed him.</gloss>
</seg>

<seg n="7.2">
<w canon="êkwa" class="ipc" gcat="IPC" sgloss="then" stem="êkwa">êkwah</w>
<w canon="tâhkinêw" class="vta" gcat="3s3oTA" sgloss="touch" stem="tâhkin" suffix="-êw">tâhkinêw</w>
;
<w canon="ômisi" class="ipc" gcat="IPC" sgloss="thus" stem="ômisi">omis</w>
<w canon="isi" class="ipc" gcat="IPC" sgloss="thus" stem="isi">îsi</w>
<w canon="miyâhtam" class="vti" gcat="3sTI" sgloss="smell" stem="miyâht" suffix="-am">miyâhtam</w>
<w canon="ocihciy" class="ndi" gcat="0sNDIof3s" prefix="3" sgloss="hand" stem="cihciy" suffix="0">ocihciy</w>
;
<w canon="kotaka" class="pr" gcat="3oPR" sgloss="other" stem="kotak" suffix="-3o">kotakah</w>
<w canon="mîna" class="ipc" gcat="IPC" sgloss="also" stem="mîna">mînah</w>
<w canon="ôhi" class="dem" gcat="3oDEM" sgloss="this" stem="awa" suffix="-3o">ôh</w>
<w canon="ôtê" class="ipc" gcat="IPC" sgloss="over_here" stem="ôtê">ôtê</w>
.
<gloss>So he touched one; he smelled his hand like this; and then the other one.</gloss>
</seg>

<seg n="7.3">
<w canon="omôhkomân" class="ni" gcat="0sNIof3s" prefix="3" sgloss="knife" stem="môhkomân" suffix="0">omôhkomân</w>
<w canon="otinam" class="vti" gcat="3sTI" sgloss="take" stem="otin" suffix="-am">otinam</w>
.
<gloss>He took his knife.</gloss>
</seg>
</p>

<p n="8">

<seg n="8.1">
<w canon="ômisi" class="ipc" gcat="IPC" sgloss="thus" stem="ômisi">omisîh</w>
<w canon="itêw" class="vta" gcat="3s3oTA" sgloss="say_to" stem="it" suffix="-êw">itêw</w>
:
<q>
<w canon="kiya" class="pr" gcat="2sPR" sgloss="you" stem="kiya">kiya</w>
<w canon="kiwîhkimâkosin" class="vai" gcat="2sAI" prefix="2" sgloss="smell_good" stem="wîhkimâkosi" suffix="-n">kiwîhkimâkosin</w>
;
<w canon="kiya" class="pr" gcat="2sPR" sgloss="you" stem="kiya">kiyah</w>
<w canon="kimiyosin" class="vai" gcat="2sAI" prefix="2" sgloss="be_good" stem="miyosi" suffix="-n">kimiyosin</w>
,</q>
<w canon="itêw" class="vta" gcat="3s3oTA" sgloss="say_to" stem="it" suffix="-êw">itêw</w>
<w canon="iyâpêsisa" class="na" gcat="3oNA" sgloss="young_bull" stem="iyâpêsis" suffix="-a">iyâpêsisah</w>
.
<gloss>He said to him, “You, you smell good; you, you are handsome,” he said to the young steer.</gloss>
</seg>
</p>

<p n="9">

<seg n="9.1">
<w canon="miywêyihtam" class="vti" gcat="3sTI" sgloss="consider_good" stem="miywêyiht" suffix="-am">miywêyihtam</w>
<w canon="iyâpêsis" class="na" gcat="3sNA" sgloss="young_bull" stem="iyâpêsis" suffix="0">iyâpêsis</w>
<w canon="ê-miyosit" class="vai" gcat="3sAIcnj" preverbs="ê|cnj" sgloss="be_good" stem="miyosi" suffix="-t">êh-miyosit</w>
,
<w canon="ê-itêyihtahk" class="vti" gcat="3sTIcnj" preverbs="ê|cnj" sgloss="think_of" stem="itêyiht" suffix="-ahk">êh-itêyihtahk</w>
.
<gloss>The steer was glad to think himself beautiful.</gloss>
</seg>

<seg n="9.2">
<w canon="omôhkomân" class="ni" gcat="0sNIof3s" prefix="3" sgloss="knife" stem="môhkomân" suffix="0">omôhkomân</w>
<w canon="tahkamêw" class="vta" gcat="3s3oTA" sgloss="stab" stem="tahkam" suffix="-êw">tahkamêw</w>
<w canon="watâyihk" class="ndi" gcat="0locNDIof3o" prefix="3" sgloss="belly" stem="atay" suffix="-iyihk">watayihk</w>
.
<gloss>He stabbed him in the belly with his knife.</gloss>
</seg>

<seg n="9.3">
<w canon="tapasîyiwa" class="vai" gcat="3oAI" sgloss="flee" stem="tapasî" suffix="-yiwa">tapasiyiwa</w>
.
<gloss>The other one ran away.</gloss>
</seg>
</p>

<p n="10">

<seg n="10.1">
<q rend="PRE 1 POST0">
<w canon="maci-kakêpâtis" class="na" gcat="3sNA" prenouns="maci|bad" sgloss="stupid_person" stem="kakêpâtis" suffix="0">macih-kakêpâtis</w>
!
<w canon="tânita" class="ipc" gcat="IPC" sgloss="where" stem="tânita">tânitah</w>
<w canon="kê-wîhkimâkosit" class="vai" gcat="3sAIcnj" preverbs="kê|IC+FUT" sgloss="smell_good" stem="wîhkimâkosi" suffix="-t">kê-wîhkimâkosit</w>
!</q>
<gloss>[“]Stupid fool! How should he smell good?</gloss>
</seg>

<seg n="10.2">
<q rend="PRE 0 POST1">
<w canon="ninôhtêhkatêwâh" class="vai" gcat="1sAIhrel" prefix="1" sgloss="be_hungry" stem="nôhtêhkatê" suffix="-wâh">ninôhtêhkatêwâh</w>
!</q>
<gloss>It is hungry I was!”</gloss>
</seg>
</p>

<p n="11">

<seg n="11.1">
<w canon="nipahêw" class="vta" gcat="3s3oTA" sgloss="kill" stem="nipah" suffix="-êw">nipahêw</w>
;
<w canon="nipiw" class="vai" gcat="3sAI" sgloss="die" stem="nipi" suffix="-w">nipiw</w>
<w canon="awa" class="dem" gcat="3sDEM" sgloss="this" stem="awa">awah</w>
<w canon="iyâpêsis" class="na" gcat="3sNA" sgloss="young_bull" stem="iyâpêsis" suffix="0">iyâpêsis</w>
.
<gloss>He killed it; the young steer died.</gloss>
</seg>

<seg n="11.2">
<w canon="êkosi" class="ipc" gcat="IPC" sgloss="thus" stem="êkosi">êkosi</w>
<w canon="ê-pahkisiniyit" class="vai" gcat="3oAIcnj" preverbs="ê|cnj" sgloss="fall" stem="pahkisin" suffix="-yit">êh-pahkisiniyit</w>
,
<w canon="ê-nipiyit" class="vai" gcat="3oAIcnj" preverbs="ê|cnj" sgloss="die" stem="nipi" suffix="-yit">êh-nipiyit</w>
,
<w canon="itohtêw" class="vai" gcat="3sAI" sgloss="go" stem="itohtê" suffix="-w">itohtêw</w>
<w canon="wîsahkêcâhk" class="na" gcat="3sNA" sgloss="Wisahketchahk" stem="wîsahkêcâhkw" suffix="0">wîsahkêcâhk</w>
.
<gloss>So when it fell down dead, Wisahketchahk walked up to it.</gloss>
</seg>
</p>

<p n="12">

<seg n="12.1">
<q>
<w canon="hay" class="interj" gcat="INTERJ" sgloss="hay" stem="hay">hay</w>
<w canon="hay" class="interj" gcat="INTERJ" sgloss="hay" stem="hay">hay</w>
<w canon="hay" class="interj" gcat="INTERJ" sgloss="hay" stem="hay">hay</w>
!
<w canon="êkwa" class="ipc" gcat="IPC" sgloss="then" stem="êkwa">êkwah</w>
<w canon="nika-mîcison" class="vai" gcat="1sAI" prefix="1" preverbs="ka|will" sgloss="eat" stem="mîciso" suffix="-n">nika-mîcison</w>
,</q>
<w canon="itwêw" class="vai" gcat="3sAI" sgloss="say" stem="itwê" suffix="-w">itwêw</w>
.
<gloss>“Splendid! Now I shall eat,” he said.</gloss>
</seg>
</p>

<p n="13">

<seg n="13.1">
<w canon="êkwa" class="ipc" gcat="IPC" sgloss="then" stem="êkwa">êkwah</w>
<w canon="wiyanihêw" class="vta" gcat="3s3oTA" sgloss="skin" stem="wiyanih" suffix="-êw">wiyinihêw</w>
,
<w canon="ê-pahkwêkiswât" class="vta" gcat="3s3oTAcnj" preverbs="ê|cnj" sgloss="flay" stem="pahkwêkisw" suffix="-ât">êh-pahkwêkiswât</w>
.
<gloss>Then he cut it up, stripping off the hide with his knife.</gloss>
</seg>
</p>

<p n="14">

<seg n="14.1">
<w canon="êkwa" class="ipc" gcat="IPC" sgloss="then" stem="êkwa">êkwah</w>
<w canon="ômisi" class="ipc" gcat="IPC" sgloss="thus" stem="ômisi">omis</w>
<w canon="itwêw" class="vai" gcat="3sAI" sgloss="say" stem="itwê" suffix="-w">îtwêw</w>
<w canon="wîsahkêcâhk" class="na" gcat="3sNA" sgloss="Wisahketchahk" stem="wîsahkêcâhkw" suffix="0">wîsahkêcâhk</w>
:
<q>
<w canon="wiyin" class="ni" gcat="0sNI" sgloss="fat" stem="wiyinw" suffix="0">wiyin</w>
<w canon="nika-ayân" class="vai" gcat="1sAI" prefix="1" preverbs="ka|will" sgloss="have" stem="ayâ" suffix="-n">nikah-ayân</w>
,</q>
<w canon="itwêw" class="vai" gcat="3sAI" sgloss="say" stem="itwê" suffix="-w">itwêw</w>
.
<gloss>Then thus spoke Wisahketchahk: “I shall have the fat meat,” he said.</gloss>
</seg>
</p>

<p n="15">

<seg n="15.1">
<w canon="ôma" class="dem" gcat="0sDEM" sgloss="this" stem="ôma">oma</w>
<w canon="ospiton" class="ndi" gcat="0sNDIof3s" prefix="3" sgloss="arm" stem="spiton" suffix="0">ôspiton</w>
,
<w canon="wîsahkêcâhk" class="na" gcat="3sNA" sgloss="Wisahketchahk" stem="wîsahkêcâhkw" suffix="0">wîsahkêcâhk</w>
<w canon="ospiton" class="ndi" gcat="0sNDIof3s" prefix="3" sgloss="arm" stem="spiton" suffix="0">ospiton</w>
<q>
<w canon="namôya" class="ipc" gcat="IPC" sgloss="not" stem="namôya">namôya</w>
!</q>
<w canon="itwêw" class="vai" gcat="3sAI" sgloss="say" stem="itwê" suffix="-w">itwêw</w>
,
<q>
<w canon="niya" class="pr" gcat="1sPR" sgloss="I" stem="niya">niya</w>
<w canon="nika-ayân" class="vai" gcat="1sAI" prefix="1" preverbs="ka|will" sgloss="have" stem="ayâ" suffix="-n">nikah-ayân</w>
<w canon="wiyin" class="ni" gcat="0sNI" sgloss="fat" stem="wiyinw" suffix="0">wiyin</w>
,</q>
<w canon="itwêw" class="vai" gcat="3sAI" sgloss="say" stem="itwê" suffix="-w">itwêw</w>
.
<gloss>His arm, Wisahketchahk's one arm, said, “No! It is I shall have the fat meat,” it said.</gloss>
</seg>
</p>

<p n="16">

<seg n="16.1">
<w canon="kotak" class="pr" gcat="0sPR" sgloss="other" stem="kotak">kotak</w>
<w canon="ospiton" class="ndi" gcat="0sNDIof3s" prefix="3" sgloss="arm" stem="spiton" suffix="0">ospiton</w>
:
<q>
<w canon="namôya" class="ipc" gcat="IPC" sgloss="not" stem="namôya">namôya</w>
!
<w canon="niya" class="pr" gcat="1sPR" sgloss="I" stem="niya">niyah</w>
<w canon="nika-ayân" class="vai" gcat="1sAI" prefix="1" preverbs="ka|will" sgloss="have" stem="ayâ" suffix="-n">nik-âyân</w>
.</q>
<gloss>His other arm said, “No! It is I shall have it.”</gloss>
</seg>
</p>

<p n="17">

<seg n="17.1">
<w canon="êkosi" class="ipc" gcat="IPC" sgloss="thus" stem="êkosi">êkosi</w>
<w canon="pîkiskwêwak" class="vai" gcat="3pAI" sgloss="use_words" stem="pîkiskwê" suffix="-wak">pîkiskwêwak</w>
,
<w canon="tâpiskôc" class="ipc" gcat="IPC" sgloss="like" stem="tâpiskôc">tâpiskôc</w>
<w canon="nisto" class="ipc" gcat="IPC" sgloss="three" stem="nisto">nisto</w>
<w canon="ayîsiyiniwak" class="na" gcat="3pNA" sgloss="person" stem="ayisiyiniw" suffix="-ak">ayîsiyiniwak</w>
,
<w canon="ê-pêyakot" class="vai" gcat="3sAIcnj" preverbs="ê|cnj" sgloss="be_alone" stem="pêyako" suffix="-t">êh-pêyakot</w>
<w canon="wîsahkêcâhk" class="na" gcat="3sNA" sgloss="Wisahketchahk" stem="wîsahkêcâhkw" suffix="0">wîsahkêcâhk</w>
.
<gloss>So they spoke, as if they were three persons, though there was only Wisahketchahk.</gloss>
</seg>

<seg n="17.2">
<w canon="kisiwâsiw" class="vai" gcat="3sAI" sgloss="be_angry" stem="kisiwâsi" suffix="-w">kisiwâsiw</w>
<w canon="âsay" class="ipc" gcat="IPC" sgloss="already" stem="âsay">âsay</w>
<w canon="awa" class="dem" gcat="3sDEM" sgloss="this" stem="awa">awa</w>
;
<w canon="awa" class="dem" gcat="3sDEM" sgloss="this" stem="awa">awa</w>
<w canon="mîna" class="ipc" gcat="IPC" sgloss="also" stem="mîna">mîna</w>
<w canon="kisiwâsiw" class="vai" gcat="3sAI" sgloss="be_angry" stem="kisiwâsi" suffix="-w">kisiwâsiw</w>
.
<gloss>The one had already grown angry; now the other, too, got into a rage.</gloss>
</seg>
</p>

<p n="18">

<seg n="18.1">
<q>
<w canon="namôya" class="ipc" gcat="IPC" sgloss="not" stem="namôya">namoya</w>
<w canon="kika-ayân" class="vai" gcat="2sAI" prefix="2" preverbs="ka|will" sgloss="have" stem="ayâ" suffix="-n">kik-âyân</w>
<w canon="wiyin" class="ni" gcat="0sNI" sgloss="fat" stem="wiyinw" suffix="0">wiyin</w>
;
<w canon="niya" class="pr" gcat="1sPR" sgloss="I" stem="niya">niyah</w>
<w canon="niwî-ayân" class="vai" gcat="1sAI" prefix="1" preverbs="wî|will" sgloss="have" stem="ayâ" suffix="-n">niwîh-ayân</w>
.</q>
<gloss>“You shan't have the fat meat! I, I shall have it!”</gloss>
</seg>
</p>

<p n="19">

<seg n="19.1">
<w canon="wîsahkêcâhk" class="na" gcat="3sNA" sgloss="Wisahketchahk" stem="wîsahkêcâhkw" suffix="0">wîsahkêcâhk</w>
<w canon="ômisi" class="ipc" gcat="IPC" sgloss="thus" stem="ômisi">ômisi</w>
<w canon="pîkiskwêw" class="vai" gcat="3sAI" sgloss="use_words" stem="pîkiskwê" suffix="-w">pîkiskwêw</w>
:
<q rend="PRE 1 POST0">
<w canon="êkâ" class="ipc" gcat="IPC" sgloss="not_to" stem="êkâ">êkâ</w>
<w canon="wiya" class="ipc" gcat="IPC" sgloss="WIYA" stem="wiya">wiyah</w>
,
<w canon="nisîmitik" class="nda" extra="vocp" gcat="3pNDAof1svoc" prefix="1" sgloss="younger_sib" stem="sîm" suffix="-VOCp">nisîmitik</w>
!</q>
<gloss>Wisahketchahk spoke thus: “Don't, little brothers!</gloss>
</seg>

<seg n="19.2">
<q rend="PRE 0 POST1">
<w canon="konita" class="ipc" gcat="IPC" sgloss="in_vain" stem="konita">kontah</w>
<w canon="kiwî-kisiwâsinâwâw" class="vai" gcat="2pAI" prefix="2" preverbs="wî|will" sgloss="be_angry" stem="kisiwâsi" suffix="-nâwâw">kiwî-kisiwâsinâwâw</w>
<w canon="wiyâs" class="ni" gcat="0sNI" sgloss="meat" stem="wiyâs" suffix="0">wiyâs</w>
<w canon="ohci" class="ipc" gcat="IPC" sgloss="thence" stem="ohci">ohci</w>
.</q>
<gloss>Needlessly you are growing angry over this meat.”</gloss>
</seg>
</p>

<p n="20">

<seg n="20.1">
<q>
<w canon="â" class="ipc" gcat="IPC" sgloss="ah" stem="â">â</w>
,
<w canon="namôya" class="ipc" gcat="IPC" sgloss="not" stem="namôya">namowya</w>
!
<w canon="ohcitaw" class="ipc" gcat="IPC" sgloss="expressly" stem="ohcitaw">ohcitaw</w>
<w canon="ê-âsponisit" class="vai" gcat="3sAIcnj" preverbs="ê|cnj" sgloss="be_greedy" stem="âsponisi" suffix="-t">êh-âsponisit</w>
.</q>
<gloss>“Oh no! He simply insists on being selfish.”</gloss>
</seg>
</p>

<p n="21">

<seg n="21.1">
<q rend="PRE 1 POST0">
<w canon="â" class="ipc" gcat="IPC" sgloss="ah" stem="â">â</w>
,
<w canon="êkâya" class="ipc" gcat="IPC" sgloss="not_to" stem="êkâya">êkâya</w>
<w canon="nânitaw" class="ipc" gcat="IPC" sgloss="simply" stem="nânitaw">nântaw</w>
<w canon="itwê" class="vai" gcat="2sAIimp" sgloss="say" stem="itwê" suffix="0">itwê</w>
!</q>
<gloss>“Oh, keep still!</gloss>
</seg>

<seg n="21.2">
<q rend="PRE 0 POST1">
<w canon="kika-tahkamitin" class="vta" gcat="1s2sTA" prefix="2" preverbs="ka|will" sgloss="stab" stem="tahkam" suffix="-itin">kika-tahkamitin</w>
.</q>
<gloss>I'll stab you.”</gloss>
</seg>
</p>

<p n="22">

<seg n="22.1">
<q>
<w canon="â" class="ipc" gcat="IPC" sgloss="ah" stem="â">âh</w>
,
<w canon="nîsta" class="pr" gcat="1sPRc" sgloss="I" stem="nîsta">nîsta</w>
<w canon="ka-tahkamitin" class="vta" gcat="1s2sTA" preverbs="ka|will" sgloss="stab" stem="tahkam" suffix="-itin">ka-tahkamitn</w>
.</q>
<gloss>“Oho, it's I who will stab you.”</gloss>
</seg>
</p>

<p n="23">

<seg n="23.1">
<q>
<w canon="â" class="ipc" gcat="IPC" sgloss="well" stem="â">â</w>
,
<w canon="cêskwa" class="ipc" gcat="IPC" sgloss="wait" stem="cêskwa">cêskwa</w>
<w canon="nisîm" class="nda" gcat="3sNDAof1s" prefix="1" sgloss="younger_sib" stem="sîm" suffix="0">nisîm</w>
!
<w canon="namôya" class="ipc" gcat="IPC" sgloss="not" stem="namôya">namoya</w>
<w canon="ta-miywâsin" class="vii" gcat="0sII" preverbs="ta|FUT" sgloss="be_good" stem="miywâsin" suffix="0">ta-miywâsin</w>
<w canon="ta-nipahitoyêk" class="vai" gcat="2pAIcnj" preverbs="ta|FUT" sgloss="kill_e.o." stem="nipahito" suffix="-yêk">ta-nipahitoyêk</w>
<w canon="wiyâs" class="ni" gcat="0sNI" sgloss="meat" stem="wiyâs" suffix="0">wiyâs</w>
<w canon="ohci" class="ipc" gcat="IPC" sgloss="thence" stem="ohci">ohci</w>
.</q>
<gloss>“Now, wait, little brother! It wouldn't do for you two to kill each other for the sake of this meat.”</gloss>
</seg>
</p>

<p n="24">

<seg n="24.1">
<w canon="konita" class="ipc" gcat="IPC" sgloss="in_vain" stem="konita">konta</w>
<w canon="mâka" class="ipc" gcat="IPC" sgloss="but" stem="mâka">mâka</w>
<w canon="kisiwâsiw" class="vai" gcat="3sAI" sgloss="be_angry" stem="kisiwâsi" suffix="-w">kisiwâsiw</w>
.
<gloss>But he got into a foolish rage.</gloss>
</seg>
</p>

<p n="25">

<seg n="25.1">
<q>
<w canon="â" class="ipc" gcat="IPC" sgloss="ah" stem="â">â</w>
,
<w canon="êkâ" class="ipc" gcat="IPC" sgloss="not_to" stem="êkâ">êkâ</w>
<w canon="nânitaw" class="ipc" gcat="IPC" sgloss="simply" stem="nânitaw">nântaw</w>
<w canon="itwê" class="vai" gcat="2sAIimp" sgloss="say" stem="itwê" suffix="0">twê</w>
!</q>
<gloss>“Ho, keep still!”</gloss>
</seg>
</p>

<p n="26">

<seg n="26.1">
<w canon="môhkomân" class="ni" gcat="0sNI" sgloss="knife" stem="môhkomân" suffix="0">môhkomân</w>
<w canon="ômisi" class="ipc" gcat="IPC" sgloss="thus" stem="ômisi">ômisi</w>
<w canon="tahkamêw" class="vta" gcat="3s3oTA" sgloss="stab" stem="tahkam" suffix="-êw">tahkamêw</w>
;
<w canon="ôma" class="dem" gcat="0sDEM" sgloss="this" stem="ôma">ôma</w>
<w canon="ospiton" class="ndi" gcat="0sNDIof3s" prefix="3" sgloss="arm" stem="spiton" suffix="0">ospiton</w>
<w canon="tahkahtam" class="vti" gcat="3sTI" sgloss="stab" stem="tahkaht" suffix="-am">tahkahtam</w>
.
<gloss>With his knife he stabbed him like this; he stabbed that arm of his.</gloss>
</seg>

<seg n="26.2">
<w canon="kwêski" class="ipc" gcat="IPC" sgloss="changing" stem="kwêski">kwêski</w>
<w canon="miyisôw" class="vai" gcat="3sAI" sgloss="give_self" stem="miyiso" suffix="-w">miyisôw</w>
<w canon="ômisi" class="ipc" gcat="IPC" sgloss="thus" stem="ômisi">omisi</w>
<w canon="môhkomân" class="ni" gcat="0sNI" sgloss="knife" stem="môhkomân" suffix="0">môhkomân</w>
.
<gloss>Across to the other side he handed himself the knife, like this.</gloss>
</seg>

<seg n="26.3">
<w canon="kotak" class="pr" gcat="0sPR" sgloss="other" stem="kotak">kotak</w>
<w canon="mîna" class="ipc" gcat="IPC" sgloss="also" stem="mîna">mînah</w>
<w canon="ospiton" class="ndi" gcat="0sNDIof3s" prefix="3" sgloss="arm" stem="spiton" suffix="0">ospiton</w>
<w canon="tahkahtam" class="vti" gcat="3sTI" sgloss="stab" stem="tahkaht" suffix="-am">tahkahtam</w>
.
<gloss>He stabbed his other arm, too.</gloss>
</seg>

<seg n="26.4">
<w canon="êkosi" class="ipc" gcat="IPC" sgloss="thus" stem="êkosi">êkosi</w>
<w canon="êkwa" class="ipc" gcat="IPC" sgloss="then" stem="êkwa">êkwah</w>
<w canon="pahkihtin" class="vii" gcat="0sII" sgloss="fall" stem="pahkihtin" suffix="0">pahkihtin</w>
<w canon="môhkomân" class="ni" gcat="0sNI" sgloss="knife" stem="môhkomân" suffix="0">môhkomân</w>
;
<gloss>And so then the knife fell down;</gloss>
</seg>

<seg n="26.5">
<w canon="nipahêw" class="vta" gcat="3s3oTA" sgloss="kill" stem="nipah" suffix="-êw">nipahêw</w>
<w canon="ospitona" class="ndi" gcat="0pNDIof3s" prefix="3" sgloss="arm" stem="spiton" suffix="-a">ospitonah</w>
.
<gloss>he had killed his arms.</gloss>
</seg>

<seg n="26.6">
<w canon="nipahitôwak" class="vai" gcat="3pAI" sgloss="kill_e.o." stem="nipahito" suffix="-wak">nipahitôwak</w>
.
<gloss>They had killed each other.</gloss>
</seg>
</p>

<p n="27">

<seg n="27.1">
<w canon="êkwa" class="ipc" gcat="IPC" sgloss="then" stem="êkwa">êkwah</w>
<w canon="wîsahkêcâhk" class="na" gcat="3sNA" sgloss="Wisahketchahk" stem="wîsahkêcâhkw" suffix="0">wîsahkêcâhk</w>
<w canon="nîpawiw" class="vai" gcat="3sAI" sgloss="stand" stem="nîpawi" suffix="-w">nîpawiw</w>
,
<w canon="ospitona" class="ndi" gcat="0pNDIof3s" prefix="3" sgloss="arm" stem="spiton" suffix="-a">ospitonah</w>
<w canon="ômisi" class="ipc" gcat="IPC" sgloss="thus" stem="ômisi">ômisi</w>
.
<gloss>There stood Wisahketchahk, with his arms like this.</gloss>
</seg>

<seg n="27.2">
<w canon="êkwa" class="ipc" gcat="IPC" sgloss="then" stem="êkwa">êkwah</w>
<w canon="wîsahkêcâhk" class="na" gcat="3sNA" sgloss="Wisahketchahk" stem="wîsahkêcâhkw" suffix="0">wîsahkêcâhk</w>
<w canon="namôya" class="ipc" gcat="IPC" sgloss="not" stem="namôya">namôya</w>
<w canon="mîcisôw" class="vai" gcat="3sAI" sgloss="eat" stem="mîciso" suffix="-w">mîcisôw</w>
;
<w canon="sipwêhtêw" class="vai" gcat="3sAI" sgloss="leave" stem="sipwêhtê" suffix="-w">sipwêhtêw</w>
;
<w canon="nakatam" class="vti" gcat="3sTI" sgloss="leave_behind" stem="nakat" suffix="-am">nakatam</w>
<w canon="wiyâs" class="ni" gcat="0sNI" sgloss="meat" stem="wiyâs" suffix="0">wiyâs</w>
.
<gloss>And Wisahketchahk did not eat; he went away; he left the meat.</gloss>
</seg>

<seg n="27.3">
<w canon="ayis" class="ipc" gcat="IPC" sgloss="for" stem="ayis">ayis</w>
<w canon="ospitona" class="ndi" gcat="0pNDIof3s" prefix="3" sgloss="arm" stem="spiton" suffix="-a">ospitonah</w>
<w canon="âhkosiw" class="vai" gcat="3sAI" sgloss="be_sick" stem="âhkosi" suffix="-w">âhkosiw</w>
;
<w canon="nipiyiwa" class="vai" gcat="3oAI" sgloss="die" stem="nipi" suffix="-yiwa">nipiyiwah</w>
<w canon="ospitona" class="ndi" gcat="0pNDIof3s" prefix="3" sgloss="arm" stem="spiton" suffix="-a">ospitonah</w>
;
<w canon="namôya" class="ipc" gcat="IPC" sgloss="not" stem="namôya">namoya</w>
<w canon="kî-miciminam" class="vti" gcat="3sTI" preverbs="kî|PAST" sgloss="hold_on_to" stem="micimin" suffix="-am">kîh-miciminam</w>
<w canon="môhkomân" class="ni" gcat="0sNI" sgloss="knife" stem="môhkomân" suffix="0">môhkomân</w>
.
<gloss>For he was sick in his arms; in fact, his arms had died; he was not able to hold a knife.</gloss>
</seg>
</p>

<p n="28">

<seg n="28.1">
<w canon="êkosi" class="ipc" gcat="IPC" sgloss="thus" stem="êkosi">êkosi</w>
<w canon="êyoko" class="pr" gcat="PR" sgloss="that_one" stem="êwako">êyakôw</w>
<w canon="âtayôhkêwin" class="ni" gcat="0sNI" sgloss="sacred_story" stem="âtayôhkêwin" suffix="0">âtiyôhkêwin</w>
.
<gloss>Thus goes this sacred story.</gloss>
</seg>
</p>
</body>
</text>
</tei.2>
